<keymap version="1" name="Windows Proper Redo" parent="$default">
  <action id="$Redo">
    <keyboard-shortcut first-keystroke="shift ctrl z" />
    <keyboard-shortcut first-keystroke="shift alt back_space" />
    <keyboard-shortcut first-keystroke="ctrl y" />
  </action>
  <action id="EditorDeleteLine" />
  <action id="NewClass">
    <keyboard-shortcut first-keystroke="alt n" second-keystroke="j" />
  </action>
  <action id="NewDir">
    <keyboard-shortcut first-keystroke="alt n" second-keystroke="p" />
  </action>
  <action id="NewFile">
    <keyboard-shortcut first-keystroke="alt n" second-keystroke="f" />
  </action>
  <action id="NewModuleInGroup">
    <keyboard-shortcut first-keystroke="alt n" second-keystroke="a" />
  </action>
</keymap>